anek_service/__init__.py
anek_service/client_pb2.py
anek_service/client_pb2.pyi
anek_service/client_pb2_grpc.py
anek_service/py.typed
anek_service-1.0.0.dist-info/METADATA
anek_service-1.0.0.dist-info/WHEEL
anek_service-1.0.0.dist-info/top_level.txt
anek_service-1.0.0.dist-info/RECORD
