Metadata-Version: 2.1
Name: anek-service
Version: 1.0.0
Summary: GRPC client for anek_service
Author: ci
Author-email: p.a.anokhin@gmail.com
